setup.py
webpandoc/__init__.py
webpandoc.egg-info/PKG-INFO
webpandoc.egg-info/SOURCES.txt
webpandoc.egg-info/dependency_links.txt
webpandoc.egg-info/entry_points.txt
webpandoc.egg-info/requires.txt
webpandoc.egg-info/top_level.txt