Metadata-Version: 1.1
Name: webpandoc
Version: 0.0.4
Summary: Tiny (and maybe yet ugly) HTTP API that calls pandoc and returns converted documents.
Home-page: https://github.com/Leryan/python-webpandoc
Author: Florent Peterschmitt
Author-email: florent@peterschmitt.fr
License: BSD
Keywords: pandoc,web,api,http
Platform: UNKNOWN
Classifier: Development Status :: 3 - Alpha
Classifier: Programming Language :: Python :: 2.7
